gandi_update_dns/__init__.py
gandi_update_dns/application.py
gandi_update_dns-0.1.6.dist-info/entry_points.txt
gandi_update_dns-0.1.6.dist-info/WHEEL
gandi_update_dns-0.1.6.dist-info/METADATA
gandi_update_dns-0.1.6.dist-info/RECORD
